examples/__init__.py
examples/bdsim_performance_eval_example.py
examples/example-2-fig-generation.py
examples/example-3-fig-generation.py
examples/example-4-fig-generation.py
examples/example_1_sources.py
examples/example_2_sources_scope_file.py
examples/example_3_spectrum_analysis.py
examples/example_4_ook_modulation_demodulation.py
examples/fig-generation.py
examples/my-performance.py
examples/my_performance_rev2.py
examples/pyblksim_performance_eval_example.py
examples/temp.py
examples/test.py
pyblksim/__init__.py
pyblksim/sys.py
pyblksim/common/__init__.py
pyblksim/common/filters.py
pyblksim/common/math.py
pyblksim/common/sinks.py
pyblksim/common/sources.py
pyblksim/control/__init__.py
pyblksim/control/linear.py
pyblksim/sims/__init__.py
pyblksim/sims/basics.py
pyblksim-0.1.9.2.dist-info/LICENSE
pyblksim-0.1.9.2.dist-info/METADATA
pyblksim-0.1.9.2.dist-info/WHEEL
pyblksim-0.1.9.2.dist-info/top_level.txt
pyblksim-0.1.9.2.dist-info/RECORD
